cuneus/__init__.py
cuneus/cli.py
cuneus/py.typed
cuneus/core/__init__.py
cuneus/core/application.py
cuneus/core/exceptions.py
cuneus/core/extensions.py
cuneus/core/logging.py
cuneus/core/settings.py
cuneus/ext/__init__.py
cuneus/ext/health.py
cuneus-0.2.8.dist-info/METADATA
cuneus-0.2.8.dist-info/WHEEL
cuneus-0.2.8.dist-info/entry_points.txt
cuneus-0.2.8.dist-info/RECORD
