Metadata-Version: 2.4
Name: cuneus
Version: 0.2.8
Summary: ASGI application wrapper
Project-URL: Homepage, https://github.com/rmyers/cuneus
Project-URL: Documentation, https://github.com/rmyers/cuneus#readme
Project-URL: Repository, https://github.com/rmyers/cuneus
Author-email: Robert Myers <robert@julython.org>
Requires-Python: >=3.11
Requires-Dist: click>=8.0
Requires-Dist: fastapi>=0.109.0
Requires-Dist: pydantic-settings>=2.0
Requires-Dist: pydantic>=2.0
Requires-Dist: structlog>=24.1.0
Requires-Dist: svcs>=24.1.0
Requires-Dist: uvicorn[standard]>=0.27.0
Provides-Extra: all
Requires-Dist: alembic>=1.13.0; extra == 'all'
Requires-Dist: asyncpg>=0.29.0; extra == 'all'
Requires-Dist: redis>=5.0; extra == 'all'
Requires-Dist: sqlalchemy[asyncio]>=2.0; extra == 'all'
Provides-Extra: database
Requires-Dist: alembic>=1.13.0; extra == 'database'
Requires-Dist: asyncpg>=0.29.0; extra == 'database'
Requires-Dist: sqlalchemy[asyncio]>=2.0; extra == 'database'
Provides-Extra: dev
Requires-Dist: alembic>=1.13.0; extra == 'dev'
Requires-Dist: asgi-lifespan>=2.1.0; extra == 'dev'
Requires-Dist: asyncpg>=0.29.0; extra == 'dev'
Requires-Dist: httpx>=0.27; extra == 'dev'
Requires-Dist: mypy>=1.8; extra == 'dev'
Requires-Dist: pytest-asyncio>=0.23; extra == 'dev'
Requires-Dist: pytest-cov>=4.0; extra == 'dev'
Requires-Dist: pytest-mock; extra == 'dev'
Requires-Dist: pytest>=8.0; extra == 'dev'
Requires-Dist: redis>=5.0; extra == 'dev'
Requires-Dist: ruff>=0.3; extra == 'dev'
Requires-Dist: sqlalchemy[asyncio]>=2.0; extra == 'dev'
Provides-Extra: redis
Requires-Dist: redis>=5.0; extra == 'redis'
